axe_selenium_python_dev/__init__.py
axe_selenium_python_dev/axe.py
axe_selenium_python_dev/package-lock.json
axe_selenium_python_dev/package.json
axe_selenium_python_dev/node_modules/axe-core/axe.min.js
axe_selenium_python_dev/tests/__init__.py
axe_selenium_python_dev/tests/conftest.py
axe_selenium_python_dev/tests/test_axe.py
axe_selenium_python_dev/tests/test_page.html
axe_selenium_python_dev/tests/requirements/flake8.txt
axe_selenium_python_dev/tests/requirements/tests.txt
axe_selenium_python_dev/tests/src/axe.min.js
axe_selenium_python_dev-2.4.0.dist-info/LICENSE.txt
axe_selenium_python_dev-2.4.0.dist-info/METADATA
axe_selenium_python_dev-2.4.0.dist-info/WHEEL
axe_selenium_python_dev-2.4.0.dist-info/axe.min.js
axe_selenium_python_dev-2.4.0.dist-info/top_level.txt
axe_selenium_python_dev-2.4.0.dist-info/RECORD
