Metadata-Version: 2.1
Name: axe-selenium-python-dev
Version: 2.4.0
Summary: Python library to integrate axe and selenium for web                 accessibility testing.
Home-page: https://github.com/EngrSushantSharma/axe-selenium-python.git
Author: Sushant Sharma
Author-email: engrSushantSharma@gmail.com
License: Mozilla Public License 2.0 (MPL 2.0)
Keywords: axe-core selenium pytest-selenium accessibility automation mozilla
Platform: UNKNOWN
Requires-Dist: selenium (>=3.0.2)
Requires-Dist: pytest (>=3.0)
